chronulus_core/__init__.py
chronulus_core/types/__init__.py
chronulus_core/types/attribute.py
chronulus_core/types/inputs.py
chronulus_core/types/requests.py
chronulus_core/types/response.py
chronulus_core/types/risk.py
chronulus_core-0.0.27.dist-info/licenses/LICENSE
chronulus_core-0.0.27.dist-info/METADATA
chronulus_core-0.0.27.dist-info/WHEEL
chronulus_core-0.0.27.dist-info/top_level.txt
chronulus_core-0.0.27.dist-info/RECORD
