Metadata-Version: 2.4
Name: chronulus-core
Version: 0.0.27
Summary: Core components for Chronulus
Author-email: Chronulus AI <jeremy@chronulus.com>
License: MIT
Classifier: Programming Language :: Python :: 3
Classifier: Programming Language :: Python :: 3.10
Classifier: Programming Language :: Python :: 3.11
Classifier: Programming Language :: Python :: 3.12
Classifier: License :: OSI Approved :: MIT License
Requires-Python: >=3.10
License-File: LICENSE
Requires-Dist: pydantic<=2.11.3,>=2.9.0
Requires-Dist: pydantic_settings<3.0.0,~=2.6.0
Requires-Dist: pillow~=10.4.0
Requires-Dist: requests~=2.32.3
Dynamic: license-file
